forastero/__init__.py
forastero/bench.py
forastero/component.py
forastero/driver.py
forastero/event.py
forastero/io.py
forastero/monitor.py
forastero/scoreboard.py
forastero/sequence.py
forastero/transaction.py
forastero-1.2.1.dist-info/LICENSE
forastero-1.2.1.dist-info/METADATA
forastero-1.2.1.dist-info/WHEEL
forastero-1.2.1.dist-info/RECORD
