Metadata-Version: 2.3
Name: forastero
Version: 1.2.1
Summary: cocotb verification framework with the batteries included
License: Apache-2.0
Keywords: cocotb,verification,verilog,systemverilog
Author: Peter Birch
Author-email: peter@lightlogic.co.uk
Requires-Python: >=3.11,<4.0
Classifier: License :: OSI Approved :: Apache Software License
Classifier: Programming Language :: Python :: 3
Classifier: Programming Language :: Python :: 3.11
Classifier: Programming Language :: Python :: 3.12
Classifier: Programming Language :: Python :: 3.13
Requires-Dist: cocotb (>=1.9.2,<2.0.0)
Requires-Dist: tabulate (>=0.9.0,<0.10.0)
Requires-Dist: yappi (>=1.6.0,<2.0.0)
Project-URL: Documentation, http://forastero.intuity.io
